gravtools/__init__.py
gravtools/merger.py
gravtools/time.py
gravtools/constants/__init__.py
gravtools/constants/merger.py
gravtools/constants/observatory.py
gravtools/constants/tests/__init__.py
gravtools/constants/tests/test_merger.py
gravtools/constants/tests/test_observatory.py
gravtools/tests/__init__.py
gravtools/tests/test_merger.py
gravtools/tests/test_time.py
gravtools-0.1.3.dist-info/LICENSE
gravtools-0.1.3.dist-info/METADATA
gravtools-0.1.3.dist-info/WHEEL
gravtools-0.1.3.dist-info/top_level.txt
gravtools-0.1.3.dist-info/RECORD
