Metadata-Version: 2.1
Name: gravtools
Version: 0.1.3
Summary: Gravitational tools for Python
Home-page: http://github.com/JWKennington/gravtools
Author: James W. Kennington
Author-email: jameswkennington@gmail.com
License: MIT
Platform: UNKNOWN
